tradehelper/__init__.py
tradehelper/tradehelp.py
tradehelper-1.45.dist-info/METADATA
tradehelper-1.45.dist-info/WHEEL
tradehelper-1.45.dist-info/top_level.txt
tradehelper-1.45.dist-info/RECORD
