Metadata-Version: 2.1
Name: tradehelper
Version: 1.45
Home-page: https://github.com/preneeshav/tradehelp
Author: preneeshav
Author-email: preneesh1985@gmail.com 
License: MIT
Keywords: trade help
Requires-Dist: pandas
Requires-Dist: datetime
Requires-Dist: requests
Requires-Dist: numpy
